website_build_tools-0.1.12.dist-info/licenses/LICENSE
webtools/__init__.py
webtools/citations.py
webtools/code_markup.py
webtools/html.py
webtools/markup.py
webtools/py.typed
webtools/settings.py
webtools/tools.py
website_build_tools-0.1.12.dist-info/METADATA
website_build_tools-0.1.12.dist-info/WHEEL
website_build_tools-0.1.12.dist-info/top_level.txt
website_build_tools-0.1.12.dist-info/RECORD
