Metadata-Version: 2.4
Name: website-build-tools
Version: 0.1.12
Summary: tools for building websites, used by defelement.org and quadraturerules.org
Author-email: Matthew Scroggs <defelement@mscroggs.co.uk>
License: MIT License
Project-URL: homepage, https://github.com/DefElement/website-build-tools
Project-URL: repository, https://github.com/DefElement/website-build-tools
Requires-Python: >=3.10.0
License-File: LICENSE
Requires-Dist: PyGithub
Requires-Dist: pytz
Requires-Dist: pyyaml
Provides-Extra: style
Requires-Dist: ruff; extra == "style"
Requires-Dist: mypy; extra == "style"
Provides-Extra: test
Requires-Dist: pytest; extra == "test"
Provides-Extra: ci
Requires-Dist: website-build-tools[style,test]; extra == "ci"
Provides-Extra: f77
Requires-Dist: fortran77punchcards; extra == "f77"
Dynamic: license-file
